{
  "type": "minecraft:crafting_shaped",
  "category": "misc",
  "key": {
    "#": {
      "item": "minecraft:copper_block"
    },
    "E": {
      "tag": "botania:manasteel_ingots"
    },
    "O": {
      "item": "mmorpg:stone/5"
    },
    "P": {
      "item": "minecraft:paper"
    },
    "S": {
      "item": "illagerinvasion:primal_essence"
    }
  },
  "pattern": [
    "#P#",
    "OSO",
    "#E#"
  ],
  "result": {
    "item": "illagerinvasion:imbuing_table"
  },
  "show_notification": true
}