{
  "display": {
    "icon": {
      "item": "minecraft:iron_pickaxe"
    },
    "title": {
      "text": "Novice Miner",
      "color": "red",
      "bold": true
    },
    "background": "minecraft:textures/block/netherite_block.png",
    "description": "",
    "frame": "task",
    "show_toast": true,
    "announce_to_chat": false,
    "hidden": true
  },
  "criteria": {
    "requirement": {
      "trigger": "minecraft:tick",
      "conditions": {
        "player": [
          {
            "condition": "minecraft:entity_properties",
            "entity": "this",
            "predicate": {
              "nbt": "{profs:'{\"map\":{\"mining\":{\"lvl\":3}}}'}"
            }
          }
        ]
      }
    }
  }
}