{
  "exp": 400,
  "id": "stat_soul_family_jewelry_epic5",
  "mats": [
    {
      "type": "ITEM",
      "id": "mmorpg:material/mining/5",
      "num": 3
    },
    {
      "type": "ITEM",
      "id": "mmorpg:stone/3",
      "num": 12
    },
    {
      "type": "ITEM",
      "id": "blue_skies:charoite",
      "num": 1
    },
    {
      "type": "ITEM",
      "id": "blue_skies:diopside_gem",
      "num": 1
    },
    {
      "type": "ITEM",
      "id": "lightmanscurrency:coin_iron",
      "num": 5    }
  ],
  "set_tier_nbt": true,
  "profession": "gear_crafting",
  "result": "mmorpg:stat_soul/family/jewelry/epic",
  "result_num": 1,
  "tier": 5
}